<?xml version="1.0" encoding="UTF-8"?>
<spirit:component xmlns:xilinx="http://www.xilinx.com" xmlns:spirit="http://www.spiritconsortium.org/XMLSchema/SPIRIT/1685-2009" xmlns:xsi="http://www.w3.org/2001/XMLSchema-instance">
  <spirit:vendor>xilinx.com</spirit:vendor>
  <spirit:library>user</spirit:library>
  <spirit:name>matrix_processor_ctrl</spirit:name>
  <spirit:version>1.0</spirit:version>
  <spirit:busInterfaces>
    <spirit:busInterface>
      <spirit:name>clk</spirit:name>
      <spirit:busType spirit:vendor="xilinx.com" spirit:library="signal" spirit:name="clock" spirit:version="1.0"/>
      <spirit:abstractionType spirit:vendor="xilinx.com" spirit:library="signal" spirit:name="clock_rtl" spirit:version="1.0"/>
      <spirit:slave/>
      <spirit:portMaps>
        <spirit:portMap>
          <spirit:logicalPort>
            <spirit:name>CLK</spirit:name>
          </spirit:logicalPort>
          <spirit:physicalPort>
            <spirit:name>clk</spirit:name>
          </spirit:physicalPort>
        </spirit:portMap>
      </spirit:portMaps>
    </spirit:busInterface>
    <spirit:busInterface>
      <spirit:name>BRAM_A</spirit:name>
      <spirit:busType spirit:vendor="xilinx.com" spirit:library="interface" spirit:name="bram" spirit:version="1.0"/>
      <spirit:abstractionType spirit:vendor="xilinx.com" spirit:library="interface" spirit:name="bram_rtl" spirit:version="1.0"/>
      <spirit:master/>
      <spirit:portMaps>
        <spirit:portMap>
          <spirit:logicalPort>
            <spirit:name>CLK</spirit:name>
          </spirit:logicalPort>
          <spirit:physicalPort>
            <spirit:name>mem_clk_A</spirit:name>
          </spirit:physicalPort>
        </spirit:portMap>
        <spirit:portMap>
          <spirit:logicalPort>
            <spirit:name>DIN</spirit:name>
          </spirit:logicalPort>
          <spirit:physicalPort>
            <spirit:name>mem_data_in_A</spirit:name>
          </spirit:physicalPort>
        </spirit:portMap>
        <spirit:portMap>
          <spirit:logicalPort>
            <spirit:name>EN</spirit:name>
          </spirit:logicalPort>
          <spirit:physicalPort>
            <spirit:name>mem_en_A</spirit:name>
          </spirit:physicalPort>
        </spirit:portMap>
        <spirit:portMap>
          <spirit:logicalPort>
            <spirit:name>DOUT</spirit:name>
          </spirit:logicalPort>
          <spirit:physicalPort>
            <spirit:name>mem_data_out_A</spirit:name>
          </spirit:physicalPort>
        </spirit:portMap>
        <spirit:portMap>
          <spirit:logicalPort>
            <spirit:name>WE</spirit:name>
          </spirit:logicalPort>
          <spirit:physicalPort>
            <spirit:name>mem_byte_we_A</spirit:name>
          </spirit:physicalPort>
        </spirit:portMap>
        <spirit:portMap>
          <spirit:logicalPort>
            <spirit:name>ADDR</spirit:name>
          </spirit:logicalPort>
          <spirit:physicalPort>
            <spirit:name>mem_address_A</spirit:name>
          </spirit:physicalPort>
        </spirit:portMap>
        <spirit:portMap>
          <spirit:logicalPort>
            <spirit:name>RST</spirit:name>
          </spirit:logicalPort>
          <spirit:physicalPort>
            <spirit:name>mem_rst_A</spirit:name>
          </spirit:physicalPort>
        </spirit:portMap>
      </spirit:portMaps>
    </spirit:busInterface>
    <spirit:busInterface>
      <spirit:name>BRAM_B</spirit:name>
      <spirit:busType spirit:vendor="xilinx.com" spirit:library="interface" spirit:name="bram" spirit:version="1.0"/>
      <spirit:abstractionType spirit:vendor="xilinx.com" spirit:library="interface" spirit:name="bram_rtl" spirit:version="1.0"/>
      <spirit:master/>
      <spirit:portMaps>
        <spirit:portMap>
          <spirit:logicalPort>
            <spirit:name>CLK</spirit:name>
          </spirit:logicalPort>
          <spirit:physicalPort>
            <spirit:name>mem_clk_B</spirit:name>
          </spirit:physicalPort>
        </spirit:portMap>
        <spirit:portMap>
          <spirit:logicalPort>
            <spirit:name>DIN</spirit:name>
          </spirit:logicalPort>
          <spirit:physicalPort>
            <spirit:name>mem_data_in_B</spirit:name>
          </spirit:physicalPort>
        </spirit:portMap>
        <spirit:portMap>
          <spirit:logicalPort>
            <spirit:name>EN</spirit:name>
          </spirit:logicalPort>
          <spirit:physicalPort>
            <spirit:name>mem_en_B</spirit:name>
          </spirit:physicalPort>
        </spirit:portMap>
        <spirit:portMap>
          <spirit:logicalPort>
            <spirit:name>DOUT</spirit:name>
          </spirit:logicalPort>
          <spirit:physicalPort>
            <spirit:name>mem_data_out_B</spirit:name>
          </spirit:physicalPort>
        </spirit:portMap>
        <spirit:portMap>
          <spirit:logicalPort>
            <spirit:name>WE</spirit:name>
          </spirit:logicalPort>
          <spirit:physicalPort>
            <spirit:name>mem_byte_we_B</spirit:name>
          </spirit:physicalPort>
        </spirit:portMap>
        <spirit:portMap>
          <spirit:logicalPort>
            <spirit:name>ADDR</spirit:name>
          </spirit:logicalPort>
          <spirit:physicalPort>
            <spirit:name>mem_address_B</spirit:name>
          </spirit:physicalPort>
        </spirit:portMap>
        <spirit:portMap>
          <spirit:logicalPort>
            <spirit:name>RST</spirit:name>
          </spirit:logicalPort>
          <spirit:physicalPort>
            <spirit:name>mem_rst_B</spirit:name>
          </spirit:physicalPort>
        </spirit:portMap>
      </spirit:portMaps>
    </spirit:busInterface>
    <spirit:busInterface>
      <spirit:name>BRAM_C</spirit:name>
      <spirit:busType spirit:vendor="xilinx.com" spirit:library="interface" spirit:name="bram" spirit:version="1.0"/>
      <spirit:abstractionType spirit:vendor="xilinx.com" spirit:library="interface" spirit:name="bram_rtl" spirit:version="1.0"/>
      <spirit:master/>
      <spirit:portMaps>
        <spirit:portMap>
          <spirit:logicalPort>
            <spirit:name>RST</spirit:name>
          </spirit:logicalPort>
          <spirit:physicalPort>
            <spirit:name>mem_rst_C</spirit:name>
          </spirit:physicalPort>
        </spirit:portMap>
        <spirit:portMap>
          <spirit:logicalPort>
            <spirit:name>CLK</spirit:name>
          </spirit:logicalPort>
          <spirit:physicalPort>
            <spirit:name>mem_clk_C</spirit:name>
          </spirit:physicalPort>
        </spirit:portMap>
        <spirit:portMap>
          <spirit:logicalPort>
            <spirit:name>DIN</spirit:name>
          </spirit:logicalPort>
          <spirit:physicalPort>
            <spirit:name>mem_data_in_C</spirit:name>
          </spirit:physicalPort>
        </spirit:portMap>
        <spirit:portMap>
          <spirit:logicalPort>
            <spirit:name>EN</spirit:name>
          </spirit:logicalPort>
          <spirit:physicalPort>
            <spirit:name>mem_en_C</spirit:name>
          </spirit:physicalPort>
        </spirit:portMap>
        <spirit:portMap>
          <spirit:logicalPort>
            <spirit:name>DOUT</spirit:name>
          </spirit:logicalPort>
          <spirit:physicalPort>
            <spirit:name>mem_data_out_C</spirit:name>
          </spirit:physicalPort>
        </spirit:portMap>
        <spirit:portMap>
          <spirit:logicalPort>
            <spirit:name>WE</spirit:name>
          </spirit:logicalPort>
          <spirit:physicalPort>
            <spirit:name>mem_byte_we_C</spirit:name>
          </spirit:physicalPort>
        </spirit:portMap>
        <spirit:portMap>
          <spirit:logicalPort>
            <spirit:name>ADDR</spirit:name>
          </spirit:logicalPort>
          <spirit:physicalPort>
            <spirit:name>mem_address_C</spirit:name>
          </spirit:physicalPort>
        </spirit:portMap>
      </spirit:portMaps>
      <spirit:parameters>
        <spirit:parameter>
          <spirit:name>NUM_READ_OUTSTANDING</spirit:name>
          <spirit:value spirit:id="BUSIFPARAM_VALUE.BRAM_C.NUM_READ_OUTSTANDING"/>
        </spirit:parameter>
        <spirit:parameter>
          <spirit:name>NUM_WRITE_OUTSTANDING</spirit:name>
          <spirit:value spirit:id="BUSIFPARAM_VALUE.BRAM_C.NUM_WRITE_OUTSTANDING"/>
        </spirit:parameter>
      </spirit:parameters>
    </spirit:busInterface>
  </spirit:busInterfaces>
  <spirit:model>
    <spirit:views>
      <spirit:view>
        <spirit:name>xilinx_anylanguagesynthesis</spirit:name>
        <spirit:displayName>Synthesis</spirit:displayName>
        <spirit:envIdentifier>:vivado.xilinx.com:synthesis</spirit:envIdentifier>
        <spirit:language>Verilog</spirit:language>
        <spirit:modelName>matrix_processor_ctrl</spirit:modelName>
        <spirit:fileSetRef>
          <spirit:localName>xilinx_anylanguagesynthesis_view_fileset</spirit:localName>
        </spirit:fileSetRef>
        <spirit:parameters>
          <spirit:parameter>
            <spirit:name>viewChecksum</spirit:name>
            <spirit:value>945e780a</spirit:value>
          </spirit:parameter>
        </spirit:parameters>
      </spirit:view>
      <spirit:view>
        <spirit:name>xilinx_anylanguagebehavioralsimulation</spirit:name>
        <spirit:displayName>Simulation</spirit:displayName>
        <spirit:envIdentifier>:vivado.xilinx.com:simulation</spirit:envIdentifier>
        <spirit:language>Verilog</spirit:language>
        <spirit:modelName>matrix_processor_ctrl</spirit:modelName>
        <spirit:fileSetRef>
          <spirit:localName>xilinx_anylanguagebehavioralsimulation_view_fileset</spirit:localName>
        </spirit:fileSetRef>
        <spirit:parameters>
          <spirit:parameter>
            <spirit:name>viewChecksum</spirit:name>
            <spirit:value>18a459b0</spirit:value>
          </spirit:parameter>
        </spirit:parameters>
      </spirit:view>
      <spirit:view>
        <spirit:name>xilinx_xpgui</spirit:name>
        <spirit:displayName>UI Layout</spirit:displayName>
        <spirit:envIdentifier>:vivado.xilinx.com:xgui.ui</spirit:envIdentifier>
        <spirit:fileSetRef>
          <spirit:localName>xilinx_xpgui_view_fileset</spirit:localName>
        </spirit:fileSetRef>
        <spirit:parameters>
          <spirit:parameter>
            <spirit:name>viewChecksum</spirit:name>
            <spirit:value>db784075</spirit:value>
          </spirit:parameter>
        </spirit:parameters>
      </spirit:view>
    </spirit:views>
    <spirit:ports>
      <spirit:port>
        <spirit:name>clk</spirit:name>
        <spirit:wire>
          <spirit:direction>in</spirit:direction>
          <spirit:wireTypeDefs>
            <spirit:wireTypeDef>
              <spirit:typeName>std_logic</spirit:typeName>
              <spirit:viewNameRef>xilinx_anylanguagesynthesis</spirit:viewNameRef>
              <spirit:viewNameRef>xilinx_anylanguagebehavioralsimulation</spirit:viewNameRef>
            </spirit:wireTypeDef>
          </spirit:wireTypeDefs>
        </spirit:wire>
      </spirit:port>
      <spirit:port>
        <spirit:name>mem_address_A</spirit:name>
        <spirit:wire>
          <spirit:direction>out</spirit:direction>
          <spirit:vector>
            <spirit:left spirit:format="long">31</spirit:left>
            <spirit:right spirit:format="long">0</spirit:right>
          </spirit:vector>
          <spirit:wireTypeDefs>
            <spirit:wireTypeDef>
              <spirit:typeName>reg</spirit:typeName>
              <spirit:viewNameRef>xilinx_anylanguagesynthesis</spirit:viewNameRef>
              <spirit:viewNameRef>xilinx_anylanguagebehavioralsimulation</spirit:viewNameRef>
            </spirit:wireTypeDef>
          </spirit:wireTypeDefs>
        </spirit:wire>
      </spirit:port>
      <spirit:port>
        <spirit:name>mem_clk_A</spirit:name>
        <spirit:wire>
          <spirit:direction>out</spirit:direction>
          <spirit:wireTypeDefs>
            <spirit:wireTypeDef>
              <spirit:typeName>std_logic</spirit:typeName>
              <spirit:viewNameRef>xilinx_anylanguagesynthesis</spirit:viewNameRef>
              <spirit:viewNameRef>xilinx_anylanguagebehavioralsimulation</spirit:viewNameRef>
            </spirit:wireTypeDef>
          </spirit:wireTypeDefs>
        </spirit:wire>
      </spirit:port>
      <spirit:port>
        <spirit:name>mem_data_in_A</spirit:name>
        <spirit:wire>
          <spirit:direction>out</spirit:direction>
          <spirit:vector>
            <spirit:left spirit:format="long">31</spirit:left>
            <spirit:right spirit:format="long">0</spirit:right>
          </spirit:vector>
          <spirit:wireTypeDefs>
            <spirit:wireTypeDef>
              <spirit:typeName>reg</spirit:typeName>
              <spirit:viewNameRef>xilinx_anylanguagesynthesis</spirit:viewNameRef>
              <spirit:viewNameRef>xilinx_anylanguagebehavioralsimulation</spirit:viewNameRef>
            </spirit:wireTypeDef>
          </spirit:wireTypeDefs>
        </spirit:wire>
      </spirit:port>
      <spirit:port>
        <spirit:name>mem_data_out_A</spirit:name>
        <spirit:wire>
          <spirit:direction>in</spirit:direction>
          <spirit:vector>
            <spirit:left spirit:format="long">31</spirit:left>
            <spirit:right spirit:format="long">0</spirit:right>
          </spirit:vector>
          <spirit:wireTypeDefs>
            <spirit:wireTypeDef>
              <spirit:typeName>std_logic_vector</spirit:typeName>
              <spirit:viewNameRef>xilinx_anylanguagesynthesis</spirit:viewNameRef>
              <spirit:viewNameRef>xilinx_anylanguagebehavioralsimulation</spirit:viewNameRef>
            </spirit:wireTypeDef>
          </spirit:wireTypeDefs>
        </spirit:wire>
      </spirit:port>
      <spirit:port>
        <spirit:name>mem_en_A</spirit:name>
        <spirit:wire>
          <spirit:direction>out</spirit:direction>
          <spirit:wireTypeDefs>
            <spirit:wireTypeDef>
              <spirit:typeName>std_logic</spirit:typeName>
              <spirit:viewNameRef>xilinx_anylanguagesynthesis</spirit:viewNameRef>
              <spirit:viewNameRef>xilinx_anylanguagebehavioralsimulation</spirit:viewNameRef>
            </spirit:wireTypeDef>
          </spirit:wireTypeDefs>
        </spirit:wire>
      </spirit:port>
      <spirit:port>
        <spirit:name>mem_rst_A</spirit:name>
        <spirit:wire>
          <spirit:direction>out</spirit:direction>
          <spirit:wireTypeDefs>
            <spirit:wireTypeDef>
              <spirit:typeName>std_logic</spirit:typeName>
              <spirit:viewNameRef>xilinx_anylanguagesynthesis</spirit:viewNameRef>
              <spirit:viewNameRef>xilinx_anylanguagebehavioralsimulation</spirit:viewNameRef>
            </spirit:wireTypeDef>
          </spirit:wireTypeDefs>
        </spirit:wire>
      </spirit:port>
      <spirit:port>
        <spirit:name>mem_byte_we_A</spirit:name>
        <spirit:wire>
          <spirit:direction>out</spirit:direction>
          <spirit:vector>
            <spirit:left spirit:format="long">3</spirit:left>
            <spirit:right spirit:format="long">0</spirit:right>
          </spirit:vector>
          <spirit:wireTypeDefs>
            <spirit:wireTypeDef>
              <spirit:typeName>reg</spirit:typeName>
              <spirit:viewNameRef>xilinx_anylanguagesynthesis</spirit:viewNameRef>
              <spirit:viewNameRef>xilinx_anylanguagebehavioralsimulation</spirit:viewNameRef>
            </spirit:wireTypeDef>
          </spirit:wireTypeDefs>
        </spirit:wire>
      </spirit:port>
      <spirit:port>
        <spirit:name>mem_address_B</spirit:name>
        <spirit:wire>
          <spirit:direction>out</spirit:direction>
          <spirit:vector>
            <spirit:left spirit:format="long">31</spirit:left>
            <spirit:right spirit:format="long">0</spirit:right>
          </spirit:vector>
          <spirit:wireTypeDefs>
            <spirit:wireTypeDef>
              <spirit:typeName>reg</spirit:typeName>
              <spirit:viewNameRef>xilinx_anylanguagesynthesis</spirit:viewNameRef>
              <spirit:viewNameRef>xilinx_anylanguagebehavioralsimulation</spirit:viewNameRef>
            </spirit:wireTypeDef>
          </spirit:wireTypeDefs>
        </spirit:wire>
      </spirit:port>
      <spirit:port>
        <spirit:name>mem_clk_B</spirit:name>
        <spirit:wire>
          <spirit:direction>out</spirit:direction>
          <spirit:wireTypeDefs>
            <spirit:wireTypeDef>
              <spirit:typeName>std_logic</spirit:typeName>
              <spirit:viewNameRef>xilinx_anylanguagesynthesis</spirit:viewNameRef>
              <spirit:viewNameRef>xilinx_anylanguagebehavioralsimulation</spirit:viewNameRef>
            </spirit:wireTypeDef>
          </spirit:wireTypeDefs>
        </spirit:wire>
      </spirit:port>
      <spirit:port>
        <spirit:name>mem_data_in_B</spirit:name>
        <spirit:wire>
          <spirit:direction>out</spirit:direction>
          <spirit:vector>
            <spirit:left spirit:format="long">31</spirit:left>
            <spirit:right spirit:format="long">0</spirit:right>
          </spirit:vector>
          <spirit:wireTypeDefs>
            <spirit:wireTypeDef>
              <spirit:typeName>reg</spirit:typeName>
              <spirit:viewNameRef>xilinx_anylanguagesynthesis</spirit:viewNameRef>
              <spirit:viewNameRef>xilinx_anylanguagebehavioralsimulation</spirit:viewNameRef>
            </spirit:wireTypeDef>
          </spirit:wireTypeDefs>
        </spirit:wire>
      </spirit:port>
      <spirit:port>
        <spirit:name>mem_data_out_B</spirit:name>
        <spirit:wire>
          <spirit:direction>in</spirit:direction>
          <spirit:vector>
            <spirit:left spirit:format="long">31</spirit:left>
            <spirit:right spirit:format="long">0</spirit:right>
          </spirit:vector>
          <spirit:wireTypeDefs>
            <spirit:wireTypeDef>
              <spirit:typeName>std_logic_vector</spirit:typeName>
              <spirit:viewNameRef>xilinx_anylanguagesynthesis</spirit:viewNameRef>
              <spirit:viewNameRef>xilinx_anylanguagebehavioralsimulation</spirit:viewNameRef>
            </spirit:wireTypeDef>
          </spirit:wireTypeDefs>
        </spirit:wire>
      </spirit:port>
      <spirit:port>
        <spirit:name>mem_en_B</spirit:name>
        <spirit:wire>
          <spirit:direction>out</spirit:direction>
          <spirit:wireTypeDefs>
            <spirit:wireTypeDef>
              <spirit:typeName>std_logic</spirit:typeName>
              <spirit:viewNameRef>xilinx_anylanguagesynthesis</spirit:viewNameRef>
              <spirit:viewNameRef>xilinx_anylanguagebehavioralsimulation</spirit:viewNameRef>
            </spirit:wireTypeDef>
          </spirit:wireTypeDefs>
        </spirit:wire>
      </spirit:port>
      <spirit:port>
        <spirit:name>mem_rst_B</spirit:name>
        <spirit:wire>
          <spirit:direction>out</spirit:direction>
          <spirit:wireTypeDefs>
            <spirit:wireTypeDef>
              <spirit:typeName>std_logic</spirit:typeName>
              <spirit:viewNameRef>xilinx_anylanguagesynthesis</spirit:viewNameRef>
              <spirit:viewNameRef>xilinx_anylanguagebehavioralsimulation</spirit:viewNameRef>
            </spirit:wireTypeDef>
          </spirit:wireTypeDefs>
        </spirit:wire>
      </spirit:port>
      <spirit:port>
        <spirit:name>mem_byte_we_B</spirit:name>
        <spirit:wire>
          <spirit:direction>out</spirit:direction>
          <spirit:vector>
            <spirit:left spirit:format="long">3</spirit:left>
            <spirit:right spirit:format="long">0</spirit:right>
          </spirit:vector>
          <spirit:wireTypeDefs>
            <spirit:wireTypeDef>
              <spirit:typeName>reg</spirit:typeName>
              <spirit:viewNameRef>xilinx_anylanguagesynthesis</spirit:viewNameRef>
              <spirit:viewNameRef>xilinx_anylanguagebehavioralsimulation</spirit:viewNameRef>
            </spirit:wireTypeDef>
          </spirit:wireTypeDefs>
        </spirit:wire>
      </spirit:port>
      <spirit:port>
        <spirit:name>mem_address_C</spirit:name>
        <spirit:wire>
          <spirit:direction>out</spirit:direction>
          <spirit:vector>
            <spirit:left spirit:format="long">31</spirit:left>
            <spirit:right spirit:format="long">0</spirit:right>
          </spirit:vector>
          <spirit:wireTypeDefs>
            <spirit:wireTypeDef>
              <spirit:typeName>reg</spirit:typeName>
              <spirit:viewNameRef>xilinx_anylanguagesynthesis</spirit:viewNameRef>
              <spirit:viewNameRef>xilinx_anylanguagebehavioralsimulation</spirit:viewNameRef>
            </spirit:wireTypeDef>
          </spirit:wireTypeDefs>
        </spirit:wire>
      </spirit:port>
      <spirit:port>
        <spirit:name>mem_clk_C</spirit:name>
        <spirit:wire>
          <spirit:direction>out</spirit:direction>
          <spirit:wireTypeDefs>
            <spirit:wireTypeDef>
              <spirit:typeName>std_logic</spirit:typeName>
              <spirit:viewNameRef>xilinx_anylanguagesynthesis</spirit:viewNameRef>
              <spirit:viewNameRef>xilinx_anylanguagebehavioralsimulation</spirit:viewNameRef>
            </spirit:wireTypeDef>
          </spirit:wireTypeDefs>
        </spirit:wire>
      </spirit:port>
      <spirit:port>
        <spirit:name>mem_data_in_C</spirit:name>
        <spirit:wire>
          <spirit:direction>out</spirit:direction>
          <spirit:vector>
            <spirit:left spirit:format="long">31</spirit:left>
            <spirit:right spirit:format="long">0</spirit:right>
          </spirit:vector>
          <spirit:wireTypeDefs>
            <spirit:wireTypeDef>
              <spirit:typeName>reg</spirit:typeName>
              <spirit:viewNameRef>xilinx_anylanguagesynthesis</spirit:viewNameRef>
              <spirit:viewNameRef>xilinx_anylanguagebehavioralsimulation</spirit:viewNameRef>
            </spirit:wireTypeDef>
          </spirit:wireTypeDefs>
        </spirit:wire>
      </spirit:port>
      <spirit:port>
        <spirit:name>mem_data_out_C</spirit:name>
        <spirit:wire>
          <spirit:direction>in</spirit:direction>
          <spirit:vector>
            <spirit:left spirit:format="long">31</spirit:left>
            <spirit:right spirit:format="long">0</spirit:right>
          </spirit:vector>
          <spirit:wireTypeDefs>
            <spirit:wireTypeDef>
              <spirit:typeName>std_logic_vector</spirit:typeName>
              <spirit:viewNameRef>xilinx_anylanguagesynthesis</spirit:viewNameRef>
              <spirit:viewNameRef>xilinx_anylanguagebehavioralsimulation</spirit:viewNameRef>
            </spirit:wireTypeDef>
          </spirit:wireTypeDefs>
        </spirit:wire>
      </spirit:port>
      <spirit:port>
        <spirit:name>mem_en_C</spirit:name>
        <spirit:wire>
          <spirit:direction>out</spirit:direction>
          <spirit:wireTypeDefs>
            <spirit:wireTypeDef>
              <spirit:typeName>std_logic</spirit:typeName>
              <spirit:viewNameRef>xilinx_anylanguagesynthesis</spirit:viewNameRef>
              <spirit:viewNameRef>xilinx_anylanguagebehavioralsimulation</spirit:viewNameRef>
            </spirit:wireTypeDef>
          </spirit:wireTypeDefs>
        </spirit:wire>
      </spirit:port>
      <spirit:port>
        <spirit:name>mem_rst_C</spirit:name>
        <spirit:wire>
          <spirit:direction>out</spirit:direction>
          <spirit:wireTypeDefs>
            <spirit:wireTypeDef>
              <spirit:typeName>std_logic</spirit:typeName>
              <spirit:viewNameRef>xilinx_anylanguagesynthesis</spirit:viewNameRef>
              <spirit:viewNameRef>xilinx_anylanguagebehavioralsimulation</spirit:viewNameRef>
            </spirit:wireTypeDef>
          </spirit:wireTypeDefs>
        </spirit:wire>
      </spirit:port>
      <spirit:port>
        <spirit:name>mem_byte_we_C</spirit:name>
        <spirit:wire>
          <spirit:direction>out</spirit:direction>
          <spirit:vector>
            <spirit:left spirit:format="long">3</spirit:left>
            <spirit:right spirit:format="long">0</spirit:right>
          </spirit:vector>
          <spirit:wireTypeDefs>
            <spirit:wireTypeDef>
              <spirit:typeName>reg</spirit:typeName>
              <spirit:viewNameRef>xilinx_anylanguagesynthesis</spirit:viewNameRef>
              <spirit:viewNameRef>xilinx_anylanguagebehavioralsimulation</spirit:viewNameRef>
            </spirit:wireTypeDef>
          </spirit:wireTypeDefs>
        </spirit:wire>
      </spirit:port>
    </spirit:ports>
    <spirit:modelParameters>
      <spirit:modelParameter xsi:type="spirit:nameValueTypeType" spirit:dataType="integer">
        <spirit:name>ope_Idle</spirit:name>
        <spirit:displayName>Ope Idle</spirit:displayName>
        <spirit:value spirit:format="bitString" spirit:resolve="generated" spirit:id="MODELPARAM_VALUE.ope_Idle" spirit:bitStringLength="3">&quot;000&quot;</spirit:value>
      </spirit:modelParameter>
      <spirit:modelParameter spirit:dataType="integer">
        <spirit:name>ope_Add</spirit:name>
        <spirit:displayName>Ope Add</spirit:displayName>
        <spirit:value spirit:format="bitString" spirit:resolve="generated" spirit:id="MODELPARAM_VALUE.ope_Add" spirit:bitStringLength="3">&quot;001&quot;</spirit:value>
      </spirit:modelParameter>
      <spirit:modelParameter spirit:dataType="integer">
        <spirit:name>s_Idle</spirit:name>
        <spirit:displayName>S Idle</spirit:displayName>
        <spirit:value spirit:format="bitString" spirit:resolve="generated" spirit:id="MODELPARAM_VALUE.s_Idle" spirit:bitStringLength="3">&quot;000&quot;</spirit:value>
      </spirit:modelParameter>
      <spirit:modelParameter spirit:dataType="integer">
        <spirit:name>s_Read</spirit:name>
        <spirit:displayName>S Read</spirit:displayName>
        <spirit:value spirit:format="bitString" spirit:resolve="generated" spirit:id="MODELPARAM_VALUE.s_Read" spirit:bitStringLength="3">&quot;001&quot;</spirit:value>
      </spirit:modelParameter>
      <spirit:modelParameter spirit:dataType="integer">
        <spirit:name>s_Write</spirit:name>
        <spirit:displayName>S Write</spirit:displayName>
        <spirit:value spirit:format="bitString" spirit:resolve="generated" spirit:id="MODELPARAM_VALUE.s_Write" spirit:bitStringLength="3">&quot;010&quot;</spirit:value>
      </spirit:modelParameter>
      <spirit:modelParameter spirit:dataType="integer">
        <spirit:name>s_Delay</spirit:name>
        <spirit:displayName>S Delay</spirit:displayName>
        <spirit:value spirit:format="bitString" spirit:resolve="generated" spirit:id="MODELPARAM_VALUE.s_Delay" spirit:bitStringLength="3">&quot;111&quot;</spirit:value>
      </spirit:modelParameter>
      <spirit:modelParameter spirit:dataType="integer">
        <spirit:name>s_Ope</spirit:name>
        <spirit:displayName>S Ope</spirit:displayName>
        <spirit:value spirit:format="bitString" spirit:resolve="generated" spirit:id="MODELPARAM_VALUE.s_Ope" spirit:bitStringLength="3">&quot;011&quot;</spirit:value>
      </spirit:modelParameter>
      <spirit:modelParameter spirit:dataType="integer">
        <spirit:name>ope_Min</spirit:name>
        <spirit:displayName>Ope Min</spirit:displayName>
        <spirit:value spirit:format="bitString" spirit:resolve="generated" spirit:id="MODELPARAM_VALUE.ope_Min" spirit:bitStringLength="3">&quot;010&quot;</spirit:value>
      </spirit:modelParameter>
      <spirit:modelParameter spirit:dataType="integer">
        <spirit:name>ope_Mul</spirit:name>
        <spirit:displayName>Ope Mul</spirit:displayName>
        <spirit:value spirit:format="bitString" spirit:resolve="generated" spirit:id="MODELPARAM_VALUE.ope_Mul" spirit:bitStringLength="3">&quot;011&quot;</spirit:value>
      </spirit:modelParameter>
      <spirit:modelParameter spirit:dataType="integer">
        <spirit:name>ope_Tra</spirit:name>
        <spirit:displayName>Ope Tra</spirit:displayName>
        <spirit:value spirit:format="bitString" spirit:resolve="generated" spirit:id="MODELPARAM_VALUE.ope_Tra" spirit:bitStringLength="3">&quot;100&quot;</spirit:value>
      </spirit:modelParameter>
      <spirit:modelParameter spirit:dataType="integer">
        <spirit:name>ope_Det</spirit:name>
        <spirit:displayName>Ope Det</spirit:displayName>
        <spirit:value spirit:format="bitString" spirit:resolve="generated" spirit:id="MODELPARAM_VALUE.ope_Det" spirit:bitStringLength="3">&quot;101&quot;</spirit:value>
      </spirit:modelParameter>
    </spirit:modelParameters>
  </spirit:model>
  <spirit:fileSets>
    <spirit:fileSet>
      <spirit:name>xilinx_anylanguagesynthesis_view_fileset</spirit:name>
      <spirit:file>
        <spirit:name>../../../constrs_1/imports/bram_control_2.0/bram_control_ooc.xdc</spirit:name>
        <spirit:userFileType>xdc</spirit:userFileType>
        <spirit:userFileType>USED_IN_out_of_context</spirit:userFileType>
      </spirit:file>
      <spirit:file>
        <spirit:name>transpose.v</spirit:name>
        <spirit:fileType>verilogSource</spirit:fileType>
      </spirit:file>
      <spirit:file>
        <spirit:name>matrix_processor_ctrl.v</spirit:name>
        <spirit:fileType>verilogSource</spirit:fileType>
        <spirit:userFileType>CHECKSUM_49a8629b</spirit:userFileType>
      </spirit:file>
    </spirit:fileSet>
    <spirit:fileSet>
      <spirit:name>xilinx_anylanguagebehavioralsimulation_view_fileset</spirit:name>
      <spirit:file>
        <spirit:name>transpose.v</spirit:name>
        <spirit:fileType>verilogSource</spirit:fileType>
      </spirit:file>
      <spirit:file>
        <spirit:name>matrix_processor_ctrl.v</spirit:name>
        <spirit:fileType>verilogSource</spirit:fileType>
      </spirit:file>
    </spirit:fileSet>
    <spirit:fileSet>
      <spirit:name>xilinx_xpgui_view_fileset</spirit:name>
      <spirit:file>
        <spirit:name>xgui/matrix_processor_ctrl_v1_0.tcl</spirit:name>
        <spirit:fileType>tclSource</spirit:fileType>
        <spirit:userFileType>CHECKSUM_db784075</spirit:userFileType>
        <spirit:userFileType>XGUI_VERSION_2</spirit:userFileType>
      </spirit:file>
    </spirit:fileSet>
  </spirit:fileSets>
  <spirit:description>matrix_processor_ctrl_v1_0</spirit:description>
  <spirit:parameters>
    <spirit:parameter>
      <spirit:name>Component_Name</spirit:name>
      <spirit:value spirit:resolve="user" spirit:id="PARAM_VALUE.Component_Name" spirit:order="1">matrix_processor_ctrl_v1_0</spirit:value>
    </spirit:parameter>
    <spirit:parameter>
      <spirit:name>ope_Idle</spirit:name>
      <spirit:displayName>Ope Idle</spirit:displayName>
      <spirit:value spirit:format="bitString" spirit:resolve="user" spirit:id="PARAM_VALUE.ope_Idle" spirit:bitStringLength="3">&quot;000&quot;</spirit:value>
    </spirit:parameter>
    <spirit:parameter>
      <spirit:name>ope_Add</spirit:name>
      <spirit:displayName>Ope Add</spirit:displayName>
      <spirit:value spirit:format="bitString" spirit:resolve="user" spirit:id="PARAM_VALUE.ope_Add" spirit:bitStringLength="3">&quot;001&quot;</spirit:value>
    </spirit:parameter>
    <spirit:parameter>
      <spirit:name>s_Idle</spirit:name>
      <spirit:displayName>S Idle</spirit:displayName>
      <spirit:value spirit:format="bitString" spirit:resolve="user" spirit:id="PARAM_VALUE.s_Idle" spirit:bitStringLength="3">&quot;000&quot;</spirit:value>
    </spirit:parameter>
    <spirit:parameter>
      <spirit:name>s_Read</spirit:name>
      <spirit:displayName>S Read</spirit:displayName>
      <spirit:value spirit:format="bitString" spirit:resolve="user" spirit:id="PARAM_VALUE.s_Read" spirit:bitStringLength="3">&quot;001&quot;</spirit:value>
    </spirit:parameter>
    <spirit:parameter>
      <spirit:name>s_Write</spirit:name>
      <spirit:displayName>S Write</spirit:displayName>
      <spirit:value spirit:format="bitString" spirit:resolve="user" spirit:id="PARAM_VALUE.s_Write" spirit:bitStringLength="3">&quot;010&quot;</spirit:value>
    </spirit:parameter>
    <spirit:parameter>
      <spirit:name>s_Delay</spirit:name>
      <spirit:displayName>S Delay</spirit:displayName>
      <spirit:value spirit:format="bitString" spirit:resolve="user" spirit:id="PARAM_VALUE.s_Delay" spirit:bitStringLength="3">&quot;111&quot;</spirit:value>
    </spirit:parameter>
    <spirit:parameter>
      <spirit:name>s_Ope</spirit:name>
      <spirit:displayName>S Ope</spirit:displayName>
      <spirit:value spirit:format="bitString" spirit:resolve="user" spirit:id="PARAM_VALUE.s_Ope" spirit:bitStringLength="3">&quot;011&quot;</spirit:value>
    </spirit:parameter>
    <spirit:parameter>
      <spirit:name>ope_Min</spirit:name>
      <spirit:displayName>Ope Min</spirit:displayName>
      <spirit:value spirit:format="bitString" spirit:resolve="user" spirit:id="PARAM_VALUE.ope_Min" spirit:bitStringLength="3">&quot;010&quot;</spirit:value>
    </spirit:parameter>
    <spirit:parameter>
      <spirit:name>ope_Mul</spirit:name>
      <spirit:displayName>Ope Mul</spirit:displayName>
      <spirit:value spirit:format="bitString" spirit:resolve="user" spirit:id="PARAM_VALUE.ope_Mul" spirit:bitStringLength="3">&quot;011&quot;</spirit:value>
    </spirit:parameter>
    <spirit:parameter>
      <spirit:name>ope_Tra</spirit:name>
      <spirit:displayName>Ope Tra</spirit:displayName>
      <spirit:value spirit:format="bitString" spirit:resolve="user" spirit:id="PARAM_VALUE.ope_Tra" spirit:bitStringLength="3">&quot;100&quot;</spirit:value>
    </spirit:parameter>
    <spirit:parameter>
      <spirit:name>ope_Det</spirit:name>
      <spirit:displayName>Ope Det</spirit:displayName>
      <spirit:value spirit:format="bitString" spirit:resolve="user" spirit:id="PARAM_VALUE.ope_Det" spirit:bitStringLength="3">&quot;101&quot;</spirit:value>
    </spirit:parameter>
  </spirit:parameters>
  <spirit:vendorExtensions>
    <xilinx:coreExtensions>
      <xilinx:supportedFamilies>
        <xilinx:family xilinx:lifeCycle="Production">virtex7</xilinx:family>
        <xilinx:family xilinx:lifeCycle="Production">qvirtex7</xilinx:family>
        <xilinx:family xilinx:lifeCycle="Production">kintex7</xilinx:family>
        <xilinx:family xilinx:lifeCycle="Production">kintex7l</xilinx:family>
        <xilinx:family xilinx:lifeCycle="Production">qkintex7</xilinx:family>
        <xilinx:family xilinx:lifeCycle="Production">qkintex7l</xilinx:family>
        <xilinx:family xilinx:lifeCycle="Production">artix7</xilinx:family>
        <xilinx:family xilinx:lifeCycle="Production">artix7l</xilinx:family>
        <xilinx:family xilinx:lifeCycle="Production">aartix7</xilinx:family>
        <xilinx:family xilinx:lifeCycle="Production">qartix7</xilinx:family>
        <xilinx:family xilinx:lifeCycle="Production">zynq</xilinx:family>
        <xilinx:family xilinx:lifeCycle="Production">qzynq</xilinx:family>
        <xilinx:family xilinx:lifeCycle="Production">azynq</xilinx:family>
        <xilinx:family xilinx:lifeCycle="Production">spartan7</xilinx:family>
        <xilinx:family xilinx:lifeCycle="Production">aspartan7</xilinx:family>
        <xilinx:family xilinx:lifeCycle="Production">virtexu</xilinx:family>
        <xilinx:family xilinx:lifeCycle="Production">zynquplus</xilinx:family>
        <xilinx:family xilinx:lifeCycle="Production">virtexuplus</xilinx:family>
        <xilinx:family xilinx:lifeCycle="Production">kintexuplus</xilinx:family>
        <xilinx:family xilinx:lifeCycle="Production">kintexu</xilinx:family>
      </xilinx:supportedFamilies>
      <xilinx:taxonomies>
        <xilinx:taxonomy>/UserIP</xilinx:taxonomy>
      </xilinx:taxonomies>
      <xilinx:displayName>matrix_processor_ctrl_v1_0</xilinx:displayName>
      <xilinx:definitionSource>package_project</xilinx:definitionSource>
      <xilinx:coreRevision>47</xilinx:coreRevision>
      <xilinx:coreCreationDateTime>2018-12-09T15:45:41Z</xilinx:coreCreationDateTime>
      <xilinx:tags>
        <xilinx:tag xilinx:name="xilinx.com:user:matrix_processor_ctrl:1.0_ARCHIVE_LOCATION">c:/Users/ricky/Desktop/Xilinx-designtool/project/ip_repo/matrix_control/matrix_control.srcs/sources_1/imports/matrix_control</xilinx:tag>
      </xilinx:tags>
    </xilinx:coreExtensions>
    <xilinx:packagingInfo>
      <xilinx:xilinxVersion>2018.2</xilinx:xilinxVersion>
      <xilinx:checksum xilinx:scope="busInterfaces" xilinx:value="db7c987c"/>
      <xilinx:checksum xilinx:scope="fileGroups" xilinx:value="13ca5223"/>
      <xilinx:checksum xilinx:scope="ports" xilinx:value="58a9db63"/>
      <xilinx:checksum xilinx:scope="hdlParameters" xilinx:value="31597403"/>
      <xilinx:checksum xilinx:scope="parameters" xilinx:value="12d010ce"/>
    </xilinx:packagingInfo>
  </spirit:vendorExtensions>
</spirit:component>
